odoo/addons/hr_expense_advance_clearing/README.rst
odoo/addons/hr_expense_advance_clearing/__init__.py
odoo/addons/hr_expense_advance_clearing/__manifest__.py
odoo/addons/hr_expense_advance_clearing/data/advance_product.xml
odoo/addons/hr_expense_advance_clearing/i18n/es.po
odoo/addons/hr_expense_advance_clearing/i18n/hr_expense_advance_clearing.pot
odoo/addons/hr_expense_advance_clearing/i18n/it.po
odoo/addons/hr_expense_advance_clearing/i18n/pt_BR.po
odoo/addons/hr_expense_advance_clearing/models/__init__.py
odoo/addons/hr_expense_advance_clearing/models/account_move.py
odoo/addons/hr_expense_advance_clearing/models/hr_employee_base.py
odoo/addons/hr_expense_advance_clearing/models/hr_expense.py
odoo/addons/hr_expense_advance_clearing/models/hr_expense_sheet.py
odoo/addons/hr_expense_advance_clearing/readme/CONFIGURE.rst
odoo/addons/hr_expense_advance_clearing/readme/CONTRIBUTORS.rst
odoo/addons/hr_expense_advance_clearing/readme/DESCRIPTION.rst
odoo/addons/hr_expense_advance_clearing/readme/USAGE.rst
odoo/addons/hr_expense_advance_clearing/static/description/icon.png
odoo/addons/hr_expense_advance_clearing/static/description/index.html
odoo/addons/hr_expense_advance_clearing/tests/__init__.py
odoo/addons/hr_expense_advance_clearing/tests/test_hr_expense_advance_clearing.py
odoo/addons/hr_expense_advance_clearing/views/hr_employee_public_views.xml
odoo/addons/hr_expense_advance_clearing/views/hr_employee_views.xml
odoo/addons/hr_expense_advance_clearing/views/hr_expense_views.xml
odoo/addons/hr_expense_advance_clearing/wizard/__init__.py
odoo/addons/hr_expense_advance_clearing/wizard/account_payment_register.py
odoo14_addon_hr_expense_advance_clearing-14.0.1.5.8.dist-info/METADATA
odoo14_addon_hr_expense_advance_clearing-14.0.1.5.8.dist-info/WHEEL
odoo14_addon_hr_expense_advance_clearing-14.0.1.5.8.dist-info/top_level.txt
odoo14_addon_hr_expense_advance_clearing-14.0.1.5.8.dist-info/RECORD
